oxford_learners_scraper/__init__.py
oxford_learners_scraper/application.py
oxford_learners_scraper/import_command.py
oxford_learners_scraper/scraper.py
oxford_learners_scraper/utils.py
oxford_learners_scraper-0.2.5.dist-info/entry_points.txt
oxford_learners_scraper-0.2.5.dist-info/WHEEL
oxford_learners_scraper-0.2.5.dist-info/METADATA
oxford_learners_scraper-0.2.5.dist-info/RECORD
