Metadata-Version: 2.1
Name: oxford-learners-scraper
Version: 0.2.5
Summary: Scraper for Oxford Learners Dictionary
Author: Tadek Teleżyński
Author-email: tadekte@gmail.com
Requires-Python: >=3.6,<4.0
Classifier: Programming Language :: Python :: 3
Classifier: Programming Language :: Python :: 3.6
Classifier: Programming Language :: Python :: 3.7
Classifier: Programming Language :: Python :: 3.8
Classifier: Programming Language :: Python :: 3.9
Requires-Dist: XlsxWriter (>=1.2.7,<2.0.0)
Requires-Dist: beautifulsoup4 (>=4.8.2,<5.0.0)
Requires-Dist: cleo (>=0.7.6,<0.8.0)
Requires-Dist: newspaper3k (>=0.2.8,<0.3.0)
Requires-Dist: requests (>=2.22.0,<3.0.0)
